AUTHORS.md
LICENSE
MANIFEST.in
README.rst
VERSION
setup.py
setuptools_qmesh/__init__.py
setuptools_qmesh/dist.py
setuptools_qmesh.egg-info/PKG-INFO
setuptools_qmesh.egg-info/SOURCES.txt
setuptools_qmesh.egg-info/dependency_links.txt
setuptools_qmesh.egg-info/entry_points.txt
setuptools_qmesh.egg-info/requires.txt
setuptools_qmesh.egg-info/top_level.txt
setuptools_qmesh/command/__init__.py
setuptools_qmesh/command/check_gmsh.py
setuptools_qmesh/command/check_qgis.py
setuptools_qmesh/command/egg_info.py
tests/__init__.py
tests/acceptance/__init__.py
tests/acceptance/test_pep8.py
tests/unit/__init__.py
tests/unit/test_command_line.py