Metadata-Version: 2.1
Name: setuptools-qmesh
Version: 1.1.0
Summary: setuptools plugin for qmesh installation, packaging and testing
Home-page: https://www.qmesh.org
Author: The QMesh Development Team.
Author-email: develop@qmesh.org
License: GPLv3
Download-URL: https://bitbucket.org/qmesh-developers/setuptools-qmesh/commits/tag/v1.1.0
Keywords: GIS,mesh generation,setuptools
Platform: UNKNOWN
Provides-Extra: build_doc
